README
setup.py
coolstorybro/__init__.py
coolstorybro/coolstorybro.py
nose_coolstorybro.egg-info/PKG-INFO
nose_coolstorybro.egg-info/SOURCES.txt
nose_coolstorybro.egg-info/dependency_links.txt
nose_coolstorybro.egg-info/entry_points.txt
nose_coolstorybro.egg-info/top_level.txt