Metadata-Version: 1.0
Name: nose-coolstorybro
Version: 0.1
Summary: TL;DR
Home-page: https://github.com/benjaminws/nose-coolstorybro
Author: Benjamin W. Smith
Author-email: benjaminwarfield@just-another.net
License: BSD
Platform: UNKNOWN
Classifier: Intended Audience :: Developers
Classifier: Natural Language :: English
Classifier: Operating System :: OS Independent
Classifier: Topic :: Software Development :: Testing
Classifier: Programming Language :: Python :: 2
